absdataset/__init__.py
absdataset/pkg_data/__init__.py
absdataset/pkg_data/googleplaystore.csv
absdataset/pkg_data/hotel_bookings.csv
absdataset-1.1.0.dist-info/LICENSE
absdataset-1.1.0.dist-info/METADATA
absdataset-1.1.0.dist-info/WHEEL
absdataset-1.1.0.dist-info/top_level.txt
absdataset-1.1.0.dist-info/RECORD
