Metadata-Version: 2.1
Name: absdataset
Version: 1.1.0
Summary: A collection of dataset
Home-page: https://github.com/AbsoluteWinter/absdataset
Author: somewhatcold (AbsoluteWinter)
Author-email: this.is.a.fake.mail@fakemail.absdataset.com
License: MIT
Project-URL: Source Code, https://github.com/AbsoluteWinter/absdataset
Project-URL: Bug Tracker, https://github.com/AbsoluteWinter/absdataset/issues
Keywords: utilities
Platform: UNKNOWN
Classifier: Programming Language :: Python :: 3
Classifier: Programming Language :: Python :: 3.7
Classifier: Programming Language :: Python :: 3.8
Classifier: Programming Language :: Python :: 3.9
Classifier: Programming Language :: Python :: 3.10
Classifier: Programming Language :: Python :: 3 :: Only
Classifier: License :: OSI Approved :: MIT License
Classifier: Operating System :: OS Independent
Classifier: Development Status :: 5 - Production/Stable
Classifier: Natural Language :: English
Requires-Python: <4,>=3.7
License-File: LICENSE
Requires-Dist: pandas
Requires-Dist: typing-extensions (>=3.7.4) ; python_version == "3.7"
Provides-Extra: all
Requires-Dist: twine (>=3.7.1) ; extra == 'all'
Requires-Dist: setuptools (>=51.0.0) ; extra == 'all'
Requires-Dist: wheel ; extra == 'all'
Requires-Dist: pipx ; extra == 'all'
Requires-Dist: build ; extra == 'all'
Requires-Dist: virtualenv (>=20.13.0) ; extra == 'all'
Provides-Extra: build
Requires-Dist: build ; extra == 'build'
Provides-Extra: dev
Requires-Dist: twine (>=3.7.1) ; extra == 'dev'
Requires-Dist: setuptools (>=51.0.0) ; extra == 'dev'
Requires-Dist: wheel ; extra == 'dev'
Requires-Dist: pipx ; extra == 'dev'
Requires-Dist: build ; extra == 'dev'
Requires-Dist: virtualenv (>=20.13.0) ; extra == 'dev'
Provides-Extra: pipx
Requires-Dist: pipx ; extra == 'pipx'
Provides-Extra: setuptools
Requires-Dist: setuptools (>=51.0.0) ; extra == 'setuptools'
Provides-Extra: twine
Requires-Dist: twine (>=3.7.1) ; extra == 'twine'
Provides-Extra: virtualenv
Requires-Dist: virtualenv (>=20.13.0) ; extra == 'virtualenv'
Provides-Extra: wheel
Requires-Dist: wheel ; extra == 'wheel'
